AUTHORS
CHANGES
LICENSE
MANIFEST.in
Makefile
README
conftest.py
setup.cfg
setup.py
tox.ini
Babel_lex.egg-info/PKG-INFO
Babel_lex.egg-info/SOURCES.txt
Babel_lex.egg-info/dependency_links.txt
Babel_lex.egg-info/entry_points.txt
Babel_lex.egg-info/not-zip-safe
Babel_lex.egg-info/requires.txt
Babel_lex.egg-info/top_level.txt
babel/__init__.py
babel/_compat.py
babel/core.py
babel/dates.py
babel/global.dat
babel/localedata.py
babel/numbers.py
babel/plural.py
babel/support.py
babel/util.py
babel/localedata/aa.dat
babel/localedata/aa_DJ.dat
babel/localedata/aa_ER.dat
babel/localedata/aa_ET.dat
babel/localedata/af.dat
babel/localedata/af_NA.dat
babel/localedata/af_ZA.dat
babel/localedata/agq.dat
babel/localedata/agq_CM.dat
babel/localedata/ak.dat
babel/localedata/ak_GH.dat
babel/localedata/am.dat
babel/localedata/am_ET.dat
babel/localedata/ar.dat
babel/localedata/ar_001.dat
babel/localedata/ar_AE.dat
babel/localedata/ar_BH.dat
babel/localedata/ar_DJ.dat
babel/localedata/ar_DZ.dat
babel/localedata/ar_EG.dat
babel/localedata/ar_EH.dat
babel/localedata/ar_ER.dat
babel/localedata/ar_IL.dat
babel/localedata/ar_IQ.dat
babel/localedata/ar_JO.dat
babel/localedata/ar_KM.dat
babel/localedata/ar_KW.dat
babel/localedata/ar_LB.dat
babel/localedata/ar_LY.dat
babel/localedata/ar_MA.dat
babel/localedata/ar_MR.dat
babel/localedata/ar_OM.dat
babel/localedata/ar_PS.dat
babel/localedata/ar_QA.dat
babel/localedata/ar_SA.dat
babel/localedata/ar_SD.dat
babel/localedata/ar_SO.dat
babel/localedata/ar_SS.dat
babel/localedata/ar_SY.dat
babel/localedata/ar_TD.dat
babel/localedata/ar_TN.dat
babel/localedata/ar_YE.dat
babel/localedata/as.dat
babel/localedata/as_IN.dat
babel/localedata/asa.dat
babel/localedata/asa_TZ.dat
babel/localedata/ast.dat
babel/localedata/ast_ES.dat
babel/localedata/az.dat
babel/localedata/az_Cyrl.dat
babel/localedata/az_Cyrl_AZ.dat
babel/localedata/az_Latn.dat
babel/localedata/az_Latn_AZ.dat
babel/localedata/bas.dat
babel/localedata/bas_CM.dat
babel/localedata/be.dat
babel/localedata/be_BY.dat
babel/localedata/bem.dat
babel/localedata/bem_ZM.dat
babel/localedata/bez.dat
babel/localedata/bez_TZ.dat
babel/localedata/bg.dat
babel/localedata/bg_BG.dat
babel/localedata/bm.dat
babel/localedata/bm_Latn.dat
